{
  "subprocesoId": "N_regulacionAtencional",
  "updatedAt": "2026-02-14T18:15:19.453Z",
  "totalModelos": 1,
  "modelos": [
    {
      "modelId": "mindfulness-mbsr-contemplativo-1979",
      "modelLabel": "Mindfulness (MBSR y tradición contemplativa)",
      "modelGrupo": "Transversal",
      "modelAutores": "Jon Kabat-Zinn",
      "modelYear": 1979,
      "items": [
        {
          "codigo": "p_mind_resp_atencion_plena",
          "nombre": "Entrenamiento en atención plena a la respiración",
          "texto": "Procedimiento básico de mindfulness que utiliza la respiración como ancla atencional para estabilizar la conciencia en el momento presente. A través de la observación deliberada del ritmo respiratorio, se entrena la capacidad de redirigir la atención, reducir la dispersión mental y modular la activación fisiológica. Constituye una base transversal para la regulación autonómica y el desarrollo de presencia consciente. (Kabat-Zinn, 1990; Kabat-Zinn, 2003).",
          "sub": "N_regulacionAtencional",
          "tipo": "procedimiento"
        }
      ]
    }
  ]
}