{
  "subprocesoId": "RI_limites",
  "updatedAt": "2026-02-03T10:02:12.944Z",
  "totalModelos": 1,
  "modelos": [
    {
      "id": "h19ta64",
      "label": "Análisis Transaccional (TA)",
      "year": "1964",
      "autores": "Eric Berne",
      "grupo": "Humanista",
      "file": "data/Core/modelos/humanista/h19ta64.json",
      "matches": {
        "tecnicas": [
          {
            "id": null,
            "label": "Detección de juegos y análisis de payoff",
            "sub": "RI_limites"
          }
        ],
        "micros": []
      }
    }
  ]
}