
{
  "id": "psicoanalisis",
  "label": "Psicoanálisis",
  "modelos": [
  
{
  "id": "psicologia-individual-adler",
  "label": "Psicología individual",
  "year": 1912,
  "autores": "Alfred Adler",
  "importance": 2,
  "file": "modelos/psicoanalisis/psicologia-individual-adler.json"
},
  {
  "id": "relaciones-objeto-fairbairn",
  "label": "Relaciones de objeto (Fairbairn)",
  "year": 1952,
  "autores": "Ronald Fairbairn",
  "file": "modelos/psicoanalisis/relaciones-objeto-fairbairn.json"
},
    {
  "id": "relaciones-objeto-klein",
  "label": "Relaciones de objeto (Klein)",
  "year": 1932,
  "autores": "Melanie Klein",
  "importance": 3,
  "file": "modelos/psicoanalisis/relaciones-objeto-klein.json"
}
  ]
}


 


 

